<?xml version="1.0" encoding="utf-8"?>
<openerp>
    <data noupdate="1" >
        <!-- 
        		Sequences for account.retention
        
        --> 
        <record id="seq_type_custom_invoice_retention" model="ir.sequence.type">
            <field name="name">Custom Account Invoice Retention</field>
            <field name="code">account.retention</field>
        </record>
        <record id="seq_invoice_retention" model="ir.sequence">
            <field name="name">Custom Account Invoice Retention</field>
            <field name="code">account.retention</field>
            <field name="padding">6</field>
        </record> 
    </data>
</openerp>
